django_node_assets/__init__.py
django_node_assets/finders.py
django_node_assets/management/__init__.py
django_node_assets/management/commands/__init__.py
django_node_assets/management/commands/npminstall.py
django_node_assets-0.9.15.dist-info/licenses/LICENSE.txt
django_node_assets-0.9.15.dist-info/METADATA
django_node_assets-0.9.15.dist-info/WHEEL
django_node_assets-0.9.15.dist-info/top_level.txt
django_node_assets-0.9.15.dist-info/RECORD
