Metadata-Version: 2.4
Name: django-node-assets
Version: 0.9.15
Summary: The Django application that allows to install and serve assets via Node.js package manager infrastructure.
Author-email: Andrey Butenko <whitespysoftware@gmail.com>
License: MIT License
Project-URL: GitHub, https://github.com/whitespy/django-node-assets
Keywords: django,assets,staticfiles,Node.js,npm,package.json
Classifier: Environment :: Web Environment
Classifier: Intended Audience :: Developers
Classifier: Operating System :: OS Independent
Classifier: Programming Language :: Python
Classifier: Programming Language :: Python :: 3.9
Classifier: Programming Language :: Python :: 3.10
Classifier: Programming Language :: Python :: 3.11
Classifier: Programming Language :: Python :: 3.12
Classifier: Framework :: Django
Classifier: Framework :: Django :: 4.2
Classifier: Framework :: Django :: 5.0
Classifier: Framework :: Django :: 5.1
Classifier: Framework :: Django :: 5.2
License-File: LICENSE.txt
Provides-Extra: dev
Requires-Dist: build; extra == "dev"
Requires-Dist: ruff; extra == "dev"
Requires-Dist: twine; extra == "dev"
Dynamic: license-file
